{
	"sample_id_map": {
		"Data": 0,
		"DiPhoton": 1,
		"TTGG": 2,
		"TTGJets": 3,
		"TTJets": 4,
		"VH_M125": 5,
		"VBFH_M125": 6,
		"ttH_M125": 7,
		"ggHToDiPhoM125": 8,
		"GJets_HT-40To100": 9,
		"GJets_HT-100To200": 10,
		"GJets_HT-200To400": 11,
		"GJets_HT-400To600": 12,
		"GJets_HT-600ToInf": 13,
		"DY": 14,
		"WG": 15,
		"ZG": 16,
		"HHbbgg": 17,
		"DiPhotonLow": 18,
		"WW": 19,
		"WZ": 20,
		"ZZ": 21,
		"NMSSM_XToYHTo2G2B_MX_1000_MY_70": 1811,
		"NMSSM_XToYHTo2G2B_MX_1000_MY_80": 1812,
		"NMSSM_XToYHTo2G2B_MX_1000_MY_90": 1813,
		"NMSSM_XToYHTo2G2B_MX_1000_MY_100": 1814,
		"NMSSM_XToYHTo2G2B_MX_1000_MY_125": 1815,
		"NMSSM_XToYHTo2G2B_MX_1000_MY_150": 1816,
		"NMSSM_XToYHTo2G2B_MX_1000_MY_170": 1817,
		"NMSSM_XToYHTo2G2B_MX_1000_MY_190": 1818,
		"NMSSM_XToYHTo2G2B_MX_1000_MY_250": 1819,
		"NMSSM_XToYHTo2G2B_MX_1000_MY_300": 1820,
		"NMSSM_XToYHTo2G2B_MX_1000_MY_350": 1821,
		"NMSSM_XToYHTo2G2B_MX_1000_MY_400": 1822,
		"NMSSM_XToYHTo2G2B_MX_1000_MY_450": 1823,
		"NMSSM_XToYHTo2G2B_MX_1000_MY_500": 1824,
		"NMSSM_XToYHTo2G2B_MX_1000_MY_550": 1825,
		"NMSSM_XToYHTo2G2B_MX_1000_MY_600": 1826,
		"NMSSM_XToYHTo2G2B_MX_1000_MY_650": 1827,
		"NMSSM_XToYHTo2G2B_MX_1000_MY_700": 1828,
		"NMSSM_XToYHTo2G2B_MX_1000_MY_800": 1829,
		"NMSSM_XToYHTo2G2B_MX_240_MY_70": 111,
		"NMSSM_XToYHTo2G2B_MX_240_MY_80": 112,
		"NMSSM_XToYHTo2G2B_MX_240_MY_90": 113,
		"NMSSM_XToYHTo2G2B_MX_240_MY_100": 114,
		"NMSSM_XToYHTo2G2B_MX_280_MY_70": 211,
		"NMSSM_XToYHTo2G2B_MX_280_MY_90": 213,
		"NMSSM_XToYHTo2G2B_MX_280_MY_100": 214,
		"NMSSM_XToYHTo2G2B_MX_280_MY_125": 215,
		"NMSSM_XToYHTo2G2B_MX_280_MY_150": 216,
		"NMSSM_XToYHTo2G2B_MX_300_MY_70": 311,
		"NMSSM_XToYHTo2G2B_MX_300_MY_125": 315,
		"NMSSM_XToYHTo2G2B_MX_300_MY_150": 316,
		"NMSSM_XToYHTo2G2B_MX_300_MY_170": 317,
		"NMSSM_XToYHTo2G2B_MX_320_MY_70": 411,
		"NMSSM_XToYHTo2G2B_MX_320_MY_80": 412,
		"NMSSM_XToYHTo2G2B_MX_320_MY_90": 413,
		"NMSSM_XToYHTo2G2B_MX_320_MY_100": 414,
		"NMSSM_XToYHTo2G2B_MX_320_MY_125": 415,
		"NMSSM_XToYHTo2G2B_MX_320_MY_150": 416,
		"NMSSM_XToYHTo2G2B_MX_320_MY_170": 417,
		"NMSSM_XToYHTo2G2B_MX_320_MY_190": 418,
		"NMSSM_XToYHTo2G2B_MX_360_MY_70": 511,
		"NMSSM_XToYHTo2G2B_MX_360_MY_90": 513,
		"NMSSM_XToYHTo2G2B_MX_360_MY_100": 514,
		"NMSSM_XToYHTo2G2B_MX_360_MY_125": 515,
		"NMSSM_XToYHTo2G2B_MX_360_MY_150": 516,
		"NMSSM_XToYHTo2G2B_MX_360_MY_170": 517,
		"NMSSM_XToYHTo2G2B_MX_360_MY_190": 518,
		"NMSSM_XToYHTo2G2B_MX_400_MY_150": 616,
		"NMSSM_XToYHTo2G2B_MX_400_MY_170": 617,
		"NMSSM_XToYHTo2G2B_MX_400_MY_190": 618,
		"NMSSM_XToYHTo2G2B_MX_400_MY_250": 619,
		"NMSSM_XToYHTo2G2B_MX_450_MY_70": 711,
		"NMSSM_XToYHTo2G2B_MX_450_MY_80": 712,
		"NMSSM_XToYHTo2G2B_MX_450_MY_90": 713,
		"NMSSM_XToYHTo2G2B_MX_450_MY_125": 715,
		"NMSSM_XToYHTo2G2B_MX_450_MY_150": 716,
		"NMSSM_XToYHTo2G2B_MX_450_MY_170": 717,
		"NMSSM_XToYHTo2G2B_MX_450_MY_250": 719,
		"NMSSM_XToYHTo2G2B_MX_450_MY_300": 720,
		"NMSSM_XToYHTo2G2B_MX_500_MY_70": 811,
		"NMSSM_XToYHTo2G2B_MX_500_MY_80": 812,
		"NMSSM_XToYHTo2G2B_MX_500_MY_90": 813,
		"NMSSM_XToYHTo2G2B_MX_500_MY_125": 815,
		"NMSSM_XToYHTo2G2B_MX_500_MY_190": 818,
		"NMSSM_XToYHTo2G2B_MX_500_MY_250": 819,
		"NMSSM_XToYHTo2G2B_MX_500_MY_300": 820,
		"NMSSM_XToYHTo2G2B_MX_500_MY_350": 821,
		"NMSSM_XToYHTo2G2B_MX_550_MY_70": 911,
		"NMSSM_XToYHTo2G2B_MX_550_MY_80": 912,
		"NMSSM_XToYHTo2G2B_MX_550_MY_90": 913,
		"NMSSM_XToYHTo2G2B_MX_550_MY_100": 914,
		"NMSSM_XToYHTo2G2B_MX_550_MY_125": 915,
		"NMSSM_XToYHTo2G2B_MX_550_MY_150": 916,
		"NMSSM_XToYHTo2G2B_MX_550_MY_170": 917,
		"NMSSM_XToYHTo2G2B_MX_550_MY_190": 918,
		"NMSSM_XToYHTo2G2B_MX_550_MY_250": 919,
		"NMSSM_XToYHTo2G2B_MX_550_MY_300": 920,
		"NMSSM_XToYHTo2G2B_MX_550_MY_400": 922,
		"NMSSM_XToYHTo2G2B_MX_600_MY_80": 1012,
		"NMSSM_XToYHTo2G2B_MX_600_MY_90": 1013,
		"NMSSM_XToYHTo2G2B_MX_600_MY_125": 1015,
		"NMSSM_XToYHTo2G2B_MX_600_MY_150": 1016,
		"NMSSM_XToYHTo2G2B_MX_600_MY_170": 1017,
		"NMSSM_XToYHTo2G2B_MX_600_MY_190": 1018,
		"NMSSM_XToYHTo2G2B_MX_600_MY_250": 1019,
		"NMSSM_XToYHTo2G2B_MX_600_MY_400": 1022,
		"NMSSM_XToYHTo2G2B_MX_600_MY_450": 1023,
		"NMSSM_XToYHTo2G2B_MX_650_MY_70": 1111,
		"NMSSM_XToYHTo2G2B_MX_650_MY_80": 1112,
		"NMSSM_XToYHTo2G2B_MX_650_MY_90": 1113,
		"NMSSM_XToYHTo2G2B_MX_650_MY_100": 1114,
		"NMSSM_XToYHTo2G2B_MX_650_MY_125": 1115,
		"NMSSM_XToYHTo2G2B_MX_650_MY_150": 1116,
		"NMSSM_XToYHTo2G2B_MX_650_MY_170": 1117,
		"NMSSM_XToYHTo2G2B_MX_650_MY_190": 1118,
		"NMSSM_XToYHTo2G2B_MX_650_MY_250": 1119,
		"NMSSM_XToYHTo2G2B_MX_650_MY_300": 1120,
		"NMSSM_XToYHTo2G2B_MX_650_MY_350": 1121,
		"NMSSM_XToYHTo2G2B_MX_650_MY_400": 1122,
		"NMSSM_XToYHTo2G2B_MX_650_MY_450": 1123,
		"NMSSM_XToYHTo2G2B_MX_650_MY_500": 1124,
		"NMSSM_XToYHTo2G2B_MX_700_MY_70": 1211,
		"NMSSM_XToYHTo2G2B_MX_700_MY_80": 1212,
		"NMSSM_XToYHTo2G2B_MX_700_MY_90": 1213,
		"NMSSM_XToYHTo2G2B_MX_700_MY_100": 1214,
		"NMSSM_XToYHTo2G2B_MX_700_MY_125": 1215,
		"NMSSM_XToYHTo2G2B_MX_700_MY_150": 1216,
		"NMSSM_XToYHTo2G2B_MX_700_MY_170": 1217,
		"NMSSM_XToYHTo2G2B_MX_700_MY_190": 1218,
		"NMSSM_XToYHTo2G2B_MX_700_MY_250": 1219,
		"NMSSM_XToYHTo2G2B_MX_700_MY_300": 1220,
		"NMSSM_XToYHTo2G2B_MX_700_MY_350": 1221,
		"NMSSM_XToYHTo2G2B_MX_700_MY_400": 1222,
		"NMSSM_XToYHTo2G2B_MX_700_MY_450": 1223,
		"NMSSM_XToYHTo2G2B_MX_700_MY_500": 1224,
		"NMSSM_XToYHTo2G2B_MX_750_MY_70": 1311,
		"NMSSM_XToYHTo2G2B_MX_750_MY_80": 1312,
		"NMSSM_XToYHTo2G2B_MX_750_MY_90": 1313,
		"NMSSM_XToYHTo2G2B_MX_750_MY_100": 1314,
		"NMSSM_XToYHTo2G2B_MX_750_MY_125": 1315,
		"NMSSM_XToYHTo2G2B_MX_750_MY_170": 1317,
		"NMSSM_XToYHTo2G2B_MX_750_MY_190": 1318,
		"NMSSM_XToYHTo2G2B_MX_750_MY_250": 1319,
		"NMSSM_XToYHTo2G2B_MX_750_MY_300": 1320,
		"NMSSM_XToYHTo2G2B_MX_750_MY_350": 1321,
		"NMSSM_XToYHTo2G2B_MX_750_MY_400": 1322,
		"NMSSM_XToYHTo2G2B_MX_750_MY_450": 1323,
		"NMSSM_XToYHTo2G2B_MX_750_MY_550": 1325,
		"NMSSM_XToYHTo2G2B_MX_750_MY_600": 1326,
		"NMSSM_XToYHTo2G2B_MX_800_MY_70": 1411,
		"NMSSM_XToYHTo2G2B_MX_800_MY_125": 1415,
		"NMSSM_XToYHTo2G2B_MX_800_MY_150": 1416,
		"NMSSM_XToYHTo2G2B_MX_800_MY_190": 1418,
		"NMSSM_XToYHTo2G2B_MX_800_MY_250": 1419,
		"NMSSM_XToYHTo2G2B_MX_800_MY_300": 1420,
		"NMSSM_XToYHTo2G2B_MX_800_MY_350": 1421,
		"NMSSM_XToYHTo2G2B_MX_800_MY_400": 1422,
		"NMSSM_XToYHTo2G2B_MX_800_MY_450": 1423,
		"NMSSM_XToYHTo2G2B_MX_800_MY_500": 1424,
		"NMSSM_XToYHTo2G2B_MX_800_MY_600": 1426,
		"NMSSM_XToYHTo2G2B_MX_800_MY_650": 1427,
		"NMSSM_XToYHTo2G2B_MX_850_MY_80": 1512,
		"NMSSM_XToYHTo2G2B_MX_850_MY_90": 1513,
		"NMSSM_XToYHTo2G2B_MX_850_MY_125": 1515,
		"NMSSM_XToYHTo2G2B_MX_850_MY_150": 1516,
		"NMSSM_XToYHTo2G2B_MX_850_MY_170": 1517,
		"NMSSM_XToYHTo2G2B_MX_850_MY_190": 1518,
		"NMSSM_XToYHTo2G2B_MX_850_MY_250": 1519,
		"NMSSM_XToYHTo2G2B_MX_850_MY_300": 1520,
		"NMSSM_XToYHTo2G2B_MX_850_MY_350": 1521,
		"NMSSM_XToYHTo2G2B_MX_850_MY_400": 1522,
		"NMSSM_XToYHTo2G2B_MX_850_MY_450": 1523,
		"NMSSM_XToYHTo2G2B_MX_850_MY_500": 1524,
		"NMSSM_XToYHTo2G2B_MX_850_MY_600": 1526,
		"NMSSM_XToYHTo2G2B_MX_900_MY_80": 1612,
		"NMSSM_XToYHTo2G2B_MX_900_MY_90": 1613,
		"NMSSM_XToYHTo2G2B_MX_900_MY_100": 1614,
		"NMSSM_XToYHTo2G2B_MX_900_MY_125": 1615,
		"NMSSM_XToYHTo2G2B_MX_900_MY_150": 1616,
		"NMSSM_XToYHTo2G2B_MX_900_MY_170": 1617,
		"NMSSM_XToYHTo2G2B_MX_900_MY_190": 1618,
		"NMSSM_XToYHTo2G2B_MX_900_MY_250": 1619,
		"NMSSM_XToYHTo2G2B_MX_900_MY_300": 1620,
		"NMSSM_XToYHTo2G2B_MX_900_MY_400": 1622,
		"NMSSM_XToYHTo2G2B_MX_900_MY_450": 1623,
		"NMSSM_XToYHTo2G2B_MX_900_MY_550": 1625,
		"NMSSM_XToYHTo2G2B_MX_900_MY_600": 1626,
		"NMSSM_XToYHTo2G2B_MX_900_MY_650": 1627,
		"NMSSM_XToYHTo2G2B_MX_950_MY_80": 1712,
		"NMSSM_XToYHTo2G2B_MX_950_MY_90": 1713,
		"NMSSM_XToYHTo2G2B_MX_950_MY_100": 1714,
		"NMSSM_XToYHTo2G2B_MX_950_MY_125": 1715,
		"NMSSM_XToYHTo2G2B_MX_950_MY_150": 1716,
		"NMSSM_XToYHTo2G2B_MX_950_MY_300": 1720,
		"NMSSM_XToYHTo2G2B_MX_950_MY_350": 1721,
		"NMSSM_XToYHTo2G2B_MX_950_MY_400": 1722,
		"NMSSM_XToYHTo2G2B_MX_950_MY_450": 1723,
		"NMSSM_XToYHTo2G2B_MX_950_MY_500": 1724,
		"NMSSM_XToYHTo2G2B_MX_950_MY_550": 1725,
		"NMSSM_XToYHTo2G2B_MX_950_MY_600": 1726,
		"NMSSM_XToYHTo2G2B_MX_950_MY_700": 1728,
		"NMSSM_XToYHTo2G2B_MX_950_MY_800": 1729
	}
}
